hivemux/__init__.py
hivemux/__main__.py
hivemux/cli.py
hivemux/config.py
hivemux/model.py
hivemux/project.py
hivemux/tmux.py
hivemux/workspaces.py
hivemux-0.0.4.dist-info/licenses/LICENSE
hivemux-0.0.4.dist-info/METADATA
hivemux-0.0.4.dist-info/WHEEL
hivemux-0.0.4.dist-info/entry_points.txt
hivemux-0.0.4.dist-info/top_level.txt
hivemux-0.0.4.dist-info/RECORD
