Metadata-Version: 2.4
Name: hivemux
Version: 0.0.4
Summary: A CLI tool to help manage your tmux sessions
Requires-Python: >=3.13
License-File: LICENSE
Requires-Dist: click>=8.3.1
Requires-Dist: jinja2>=3.1.6
Dynamic: license-file
